Workbook

Sheet Resumen
A1: Numeral 11 – Costo de componentes de la tarjeta CubeSat_UD34_PCB4 (USD)
A2: Solo componentes. Excluye fabricación de PCB, ensamblaje, transporte e impuestos. No es precio de venta.
A4: Tamaño del lote | B4: Costo de componentes del lote (USD) | C4: Costo de componentes por tarjeta (USD) | D4: De ese costo: parte ESTIMADA/pendiente (USD) | E4: % estimado | F4: Observaciones
A5: 10 tarjetas | B5: =BOM_Costos!O29 -> 712.129 | C5: =B5/10 -> 71.2129 | D5: =SUMIF(BOM_Costos!$I$2:$I$28,"ESTIMADO",BOM_Costos!O2:O28) -> 53.1 | E5: =D5/B5 -> 0.074565142 | F5: Sin descuentos de volumen en la mayoría de ICs; sobrecompra por múltiplos (LCSC ×100, Samtec ×8).
A6: 100 tarjetas | B6: =BOM_Costos!T29 -> 5655.0304 | C6: =B6/100 -> 56.550304 | D6: =SUMIF(BOM_Costos!$I$2:$I$28,"ESTIMADO",BOM_Costos!T2:T28) -> 445 | E6: =D6/B6 -> 0.078691 | F6: Escalones de 100 uds en ICs y conectores; el sensor de imagen sigue dominando el costo.
A7: 1000 tarjetas | B7: =BOM_Costos!Y29 -> 49551.944 | C7: =B7/1000 -> 49.551944 | D7: =SUMIF(BOM_Costos!$I$2:$I$28,"ESTIMADO",BOM_Costos!Y2:Y28) -> 4084 | E7: =D7/B7 -> 0.082418563 | F7: Escalón de 1000 uds (carrete completo en DRV8837 y TXS0108 usa cota); sensor AR0135 sin escalón publicado a 1000.
A9: Datos del gráfico (eje X = número de tarjetas, escala log)
A10: Tarjetas | B10: USD/tarjeta
A11: 10 | B11: =C5 -> 71.2129
A12: 100 | B12: =C6 -> 56.550304
A13: 1000 | B13: =C7 -> 49.551944
A16: Mayores contribuyentes por tarjeta (USD/tarjeta)
A17: Componente | B17: 10 tarjetas | C17: 100 tarjetas | D17: 1000 tarjetas
A18: AR0135 (sensor de imagen) | B18: =BOM_Costos!O25/10 -> 23.7216 | C18: =BOM_Costos!T25/100 -> 21.411264 | D18: =BOM_Costos!Y25/1000 -> 21.411264
A19: J_ACTUATORS Harwin | B19: =BOM_Costos!O15/10 -> 12.15 | C19: =BOM_Costos!T15/100 -> 10.59 | D19: =BOM_Costos!Y15/1000 -> 7.54
A20: J1_PC104 Samtec ESQ | B20: =BOM_Costos!O14/10 -> 14.944 | C20: =BOM_Costos!T14/100 -> 7.62528 | D20: =BOM_Costos!Y14/1000 -> 5.508
A21: LSM6DSOX (IMU) | B21: =BOM_Costos!O23/10 -> 3.487 | C21: =BOM_Costos!T23/100 -> 3.0519 | D21: =BOM_Costos!Y23/1000 -> 2.78705
A22: DRV8313 (BLDC) | B22: =BOM_Costos!O28/10 -> 2.531 | C22: =BOM_Costos!T28/100 -> 2.0913 | D22: =BOM_Costos!Y28/1000 -> 1.8609
A23: Regulador MSOP-8 (ESTIMADO) | B23: =BOM_Costos!O21/10 -> 3 | C23: =BOM_Costos!T21/100 -> 3 | D23: =BOM_Costos!Y21/1000 -> 3

Sheet Supuestos
A1: Parámetro | B1: Valor | C1: Fuente / nota
A2: Fecha de consulta | B2: 2026-10-26 | C2: Precios leídos de la versión indexada de cada página el 26-oct-2026; pueden variar al abrir la página en vivo.
A3: EUR→USD | B3: 1.12 | C3: https://moneyexchangerate.org/currencyexchange/eur/usd/6 (1 EUR = 1.12 USD, 20-oct-2026). Solo se usa para AR0135 (precio en EUR).
A4: AR0135 EUR @10 | B4: 21.18 | C4: Digi-Key España (Marketplace) https://www.digikey.es/en/products/detail/onsemi/AR0135CS2C00SUEA0-DRBR/7221084
A5: AR0135 EUR @100 | B5: 19.1172 | C5: Misma página. La tabla visible llega solo a 100 uds.
A6: AR0135 EUR @1000 | B6: 19.1172 | C6: ESTIMADO: no hay escalón publicado para 1000; se mantiene el de 100 (cota superior, sin descuento adicional).
A7: Moneda del análisis | B7: USD | C7: Todos los precios en USD salvo AR0135 (EUR convertido con la tasa anterior).
A8: Configuración | B8: Todas las 27 líneas del BOM montadas (86 componentes/tarjeta) | C8: El archivo CubeSat_UD34_PCB4.xlsx no trae columna DNP/variantes: no hay componentes opcionales ni no montados identificables. Misma configuración y mismo criterio de compra en los 3 lotes.
A9: Criterio de compra | B9: Menor precio verificable en distribuidor identificable; precio según la cantidad TOTAL de piezas del lote; se respetan MOQ y múltiplos de empaque (LCSC múltiplos de 100; Samtec tubos de 8); carretes solo si la cantidad necesaria coincide con el carrete. | C9: Sobrantes declarados en cada línea.
A10: Excluido | B10: Fabricación de PCB, ensamblaje, transporte, impuestos/aranceles | C10: Según el numeral 11 de la guía.

Sheet BOM_Costos
A1: # | B1: Designadores | C1: Descripción (BOM) | D1: Cant./tarjeta | E1: Huella (BOM) | F1: Fabricante | G1: Referencia exacta (MPN) | H1: Origen del MPN | I1: Estado del precio | J1: Proveedor de referencia | K1: Moneda | L1: 10: cant. necesaria | M1: 10: cant. a comprar | N1: 10: precio unit. (USD) | O1: 10: costo (USD) | P1: 10: sobrante | Q1: 100: cant. necesaria | R1: 100: cant. a comprar | S1: 100: precio unit. (USD) | T1: 100: costo (USD) | U1: 100: sobrante | V1: 1000: cant. necesaria | W1: 1000: cant. a comprar | X1: 1000: precio unit. (USD) | Y1: 1000: costo (USD) | Z1: 1000: sobrante | AA1: Disponibilidad / plazo | AB1: Fuente (URL verificable) | AC1: Notas
A2: 1 | B2: C1_VBAT, C_3V3, C_3V3_FILT, C_a, C_b, C_IMU_VDD, C_IMU_VDDIO, C_IN2, C_MAG_VDDIO, C_VBAT_FILT, C_VCC_X/Y/Z, C_VCCA, C_VCCB, C_VCP, C_VM1, C_VM2, C_VM_X/Y/Z | C2: Chip Capacitor 100 nF ±10% 50 V 0603 | D2: 21 | E2: CAPC1608X90X40NL10T20 | F2: Samsung Electro-Mechanics | G2: CL10B104KB8NNNC | H2: Propuesto | I2: COTIZADO | J2: LCSC (C1591) | K2: USD | L2: =$D2*10 -> 210 | M2: 300 | N2: 0.0142 | O2: =M2*N2 -> 4.26 | P2: =M2-L2 -> 90 | Q2: =$D2*100 -> 2100 | R2: 2100 | S2: 0.012 | T2: =R2*S2 -> 25.2 | U2: =R2-Q2 -> 0 | V2: =$D2*1000 -> 21000 | W2: 21000 | X2: 0.011 | Y2: =W2*X2 -> 231 | Z2: =W2-V2 -> 0 | AA2: En stock (≈13.6 M uds); MOQ 100, múltiplo 100; carrete 4000 | AB2: https://www.lcsc.com/product-detail/C1591.html | AC2: Escalones LCSC: 100+ $0.0142, 1000+ $0.012, 4000+ $0.011. Lote 10: necesita 210 → se compran 300 (múltiplo de 100).
A3: 2 | B3: C_1, C_3V3_BULK, C_MAG_CAP, C_VAA_BULK, C_VDD_BULK, C_VDDIO_BULK | C3: Chip Capacitor 10 µF ±10% 16 V 0805 | D3: 6 | E3: CAPC2013X135X45NL10T25 | F3: Samsung Electro-Mechanics | G3: CL21A106KOQNNNE | H3: Propuesto | I3: ESTIMADO | J3: Sin cotización directa (referencia: familia MLCC LCSC) | K3: USD | L3: =$D3*10 -> 60 | M3: 60 | N3: 0.05 | O3: =M3*N3 -> 3 | P3: =M3-L3 -> 0 | Q3: =$D3*100 -> 600 | R3: 600 | S3: 0.04 | T3: =R3*S3 -> 24 | U3: =R3-Q3 -> 0 | V3: =$D3*1000 -> 6000 | W3: 6000 | X3: 0.035 | Y3: =W3*X3 -> 210 | Z3: =W3-V3 -> 0 | AA3: Pendiente de verificar | AC3: Orden de magnitud para MLCC 10 µF 0805 X5R en LCSC/Digi-Key; verificar antes de comprar.
A4: 3 | B4: C_CP | C4: Chip Capacitor 10 nF ±20% 50 V 0402 | D4: 1 | E4: CAPC0402(1005)60_L | F4: Samsung Electro-Mechanics | G4: CL05B103KB5NNNC | H4: Propuesto | I4: ESTIMADO | J4: Sin cotización directa (familia MLCC 0402) | K4: USD | L4: =$D4*10 -> 10 | M4: 10 | N4: 0.01 | O4: =M4*N4 -> 0.1 | P4: =M4-L4 -> 0 | Q4: =$D4*100 -> 100 | R4: 100 | S4: 0.006 | T4: =R4*S4 -> 0.6 | U4: =R4-Q4 -> 0 | V4: =$D4*1000 -> 1000 | W4: 1000 | X4: 0.004 | Y4: =W4*X4 -> 4 | Z4: =W4-V4 -> 0 | AA4: Pendiente de verificar | AC4: Estimado por analogía con CL10B104 (0603) cotizado.
A5: 4 | B5: C_IN1 | C5: Chip Capacitor 1 µF ±10% 25 V 0805 | D5: 1 | E5: CAPC2013X145X50ML20T25 | F5: Murata | G5: GRM21BR61E105KA99L | H5: Propuesto | I5: ESTIMADO | J5: Sin cotización directa | K5: USD | L5: =$D5*10 -> 10 | M5: 10 | N5: 0.03 | O5: =M5*N5 -> 0.3 | P5: =M5-L5 -> 0 | Q5: =$D5*100 -> 100 | R5: 100 | S5: 0.02 | T5: =R5*S5 -> 2 | U5: =R5-Q5 -> 0 | V5: =$D5*1000 -> 1000 | W5: 1000 | X5: 0.015 | Y5: =W5*X5 -> 15 | Z5: =W5-V5 -> 0 | AA5: Pendiente de verificar | AC5: Estimado; MLCC 1 µF 0805 típico.
A6: 5 | B6: C_OUT1 | C6: Tantalio SMD TANTAMOUNT 10 µF ±10% 16 V 1206 (caja A) | D6: 1 | E6: VISH-TR3-A_V | F6: Vishay Semiconductor | G6: TR3A106K016C1700 | H6: Propuesto | I6: ESTIMADO | J6: RS UK / Element14 (familia TR3A, GBP/SGD) | K6: USD | L6: =$D6*10 -> 10 | M6: 10 | N6: 0.7 | O6: =M6*N6 -> 7 | P6: =M6-L6 -> 0 | Q6: =$D6*100 -> 100 | R6: 100 | S6: 0.35 | T6: =R6*S6 -> 35 | U6: =R6-Q6 -> 0 | V6: =$D6*1000 -> 1000 | W6: 1000 | X6: 0.25 | Y6: =W6*X6 -> 250 | Z6: =W6-V6 -> 0 | AA6: Existencia limitada en RS UK | AB6: https://uk.rs-online.com/web/p/tantalum-capacitors/6845014 | AC6: Estimado a partir de escalones RS UK (£0.233 @250+, £0.171 @1000+) con 1 GBP≈1.30 USD (SUPUESTO). Verificar.
A7: 6 | B7: C_p_d | C7: Chip Capacitor 1 µF ±10% 16 V 0603 | D7: 1 | E7: CAPC1608X90X35ML15T15 | F7: Samsung Electro-Mechanics | G7: CL10B105KO8NNNC | H7: Propuesto | I7: ESTIMADO | J7: Sin cotización directa | K7: USD | L7: =$D7*10 -> 10 | M7: 10 | N7: 0.012 | O7: =M7*N7 -> 0.12 | P7: =M7-L7 -> 0 | Q7: =$D7*100 -> 100 | R7: 100 | S7: 0.009 | T7: =R7*S7 -> 0.9 | U7: =R7-Q7 -> 0 | V7: =$D7*1000 -> 1000 | W7: 1000 | X7: 0.007 | Y7: =W7*X7 -> 7 | Z7: =W7-V7 -> 0 | AA7: Pendiente de verificar | AC7: Estimado por analogía con CL10B104 cotizado.
A8: 7 | B8: C_V3P3 | C8: Chip Capacitor 470 nF ±20% 25 V 0603 | D8: 1 | E8: CAPC0603(1608)100_L | F8: Samsung Electro-Mechanics | G8: CL10B474KA8NNNC | H8: Propuesto | I8: ESTIMADO | J8: Sin cotización directa | K8: USD | L8: =$D8*10 -> 10 | M8: 10 | N8: 0.012 | O8: =M8*N8 -> 0.12 | P8: =M8-L8 -> 0 | Q8: =$D8*100 -> 100 | R8: 100 | S8: 0.009 | T8: =R8*S8 -> 0.9 | U8: =R8-Q8 -> 0 | V8: =$D8*1000 -> 1000 | W8: 1000 | X8: 0.007 | Y8: =W8*X8 -> 7 | Z8: =W8-V8 -> 0 | AA8: Pendiente de verificar | AC8: Estimado por analogía.
A9: 8 | B9: C_VAA1/2, C_VAAPIX1/2, C_VDD1-5, C_VDDIO1-5 | C9: Chip Capacitor 100 nF ±20% 10 V 0402 | D9: 14 | E9: CAPC0402(1005)60_L | F9: Samsung Electro-Mechanics | G9: CL05B104KP5NNNC | H9: Propuesto | I9: ESTIMADO | J9: Sin cotización directa | K9: USD | L9: =$D9*10 -> 140 | M9: 140 | N9: 0.006 | O9: =M9*N9 -> 0.84 | P9: =M9-L9 -> 0 | Q9: =$D9*100 -> 1400 | R9: 1400 | S9: 0.004 | T9: =R9*S9 -> 5.6 | U9: =R9-Q9 -> 0 | V9: =$D9*1000 -> 14000 | W9: 14000 | X9: 0.003 | Y9: =W9*X9 -> 42 | Z9: =W9-V9 -> 0 | AA9: Pendiente de verificar | AC9: Estimado; MLCC 0402 100 nF.
A10: 9 | B10: C_VBAT, C_VBAT_BULK | C10: Tantalio 47 µF ±10% 16 V 2917 (7343) | D10: 2 | E10: FP-TPSD-MFG | F10: KEMET | G10: T491D476K016AT | H10: Propuesto | I10: COTIZADO | J10: LCSC (C122248) | K10: USD | L10: =$D10*10 -> 20 | M10: 20 | N10: 0.6806 | O10: =M10*N10 -> 13.612 | P10: =M10-L10 -> 0 | Q10: =$D10*100 -> 200 | R10: 200 | S10: 0.5948 | T10: =R10*S10 -> 118.96 | U10: =R10-Q10 -> 0 | V10: =$D10*1000 -> 2000 | W10: 2000 | X10: 0.491 | Y10: =W10*X10 -> 982 | Z10: =W10-V10 -> 0 | AA10: Stock bajo en LCSC (73 uds en una captura); Digi-Key plazo 13–19 sem | AB10: https://www.lcsc.com/product-detail/C122248.html | AC10: Descripción del BOM coincide literalmente con 'CAP TANT 47UF 10% 16V 2917' (Digi-Key T491D476K016AT). Para 20 uds no se ve el escalón 10+ en la captura vigente: se usa el de 30+ (conservador).
A11: 10 | B11: C_VM_BULK | C11: Cerámico CL32 100 µF ±20% 10 V X5R 1210 | D11: 1 | E11: CAPC3225X280N | F11: Samsung Electro-Mechanics | G11: CL32A107MPVNNNE | H11: BOM (descripción) | I11: COTIZADO | J11: LCSC (C23742) | K11: USD | L11: =$D11*10 -> 10 | M11: 10 | N11: 0.2519 | O11: =M11*N11 -> 2.519 | P11: =M11-L11 -> 0 | Q11: =$D11*100 -> 100 | R11: 100 | S11: 0.1977 | T11: =R11*S11 -> 19.77 | U11: =R11-Q11 -> 0 | V11: =$D11*1000 -> 1000 | W11: 1000 | X11: 0.1627 | Y11: =W11*X11 -> 162.7 | Z11: =W11-V11 -> 0 | AA11: En stock (≈61 k uds); carrete 1000 | AB11: https://www.lcsc.com/product-detail/C23742.html | AC11: Escalones LCSC: 10+ $0.2519, 100+ $0.1977, 1000+ $0.1627.
A12: 11 | B12: D1_ESD, D1_ESD_B | C12: TVS 5.5 V SOT143B | D12: 2 | E12: FP-SOT143B-MFG | F12: Nexperia | G12: PRTR5V0U2X,215 | H12: BOM | I12: COTIZADO | J12: Digi-Key (vía agregador Ciiva) | K12: USD | L12: =$D12*10 -> 20 | M12: 20 | N12: 0.41 | O12: =M12*N12 -> 8.2 | P12: =M12-L12 -> 0 | Q12: =$D12*100 -> 200 | R12: 200 | S12: 0.2626 | T12: =R12*S12 -> 52.52 | U12: =R12-Q12 -> 0 | V12: =$D12*1000 -> 2000 | W12: 2000 | X12: 0.1786 | Y12: =W12*X12 -> 357.2 | Z12: =W12-V12 -> 0 | AA12: RIESGO: stock 0 en Digi-Key; Farnell JP lo marca 'No Longer Manufactured'; LCSC agotado | AB12: https://ciiva.com/part/prtr5v0u2x-215-26504288 | AC12: Escalones tomados de la fila Digi-Key (1: $0.66, 10: $0.41, 100: $0.2626, 1000: $0.1786). Hay precios muy dispares en otros sitios ($0.11–$2.2): verificar obsolescencia/alternativa (PRTR5V0U2AX/-F).
A13: 12 | B13: FL | C13: Ferrita/bead 0603 (sin descripción en BOM) | D13: 1 | E13: BEADC1608X95N | F13: (vacío en BOM) | G13: Sin MPN en BOM — propuesto: Murata BLM18PG221SN1D | H13: Propuesto | I13: ESTIMADO | J13: Sin cotización | K13: USD | L13: =$D13*10 -> 10 | M13: 10 | N13: 0.1 | O13: =M13*N13 -> 1 | P13: =M13-L13 -> 0 | Q13: =$D13*100 -> 100 | R13: 100 | S13: 0.06 | T13: =R13*S13 -> 6 | U13: =R13-Q13 -> 0 | V13: =$D13*1000 -> 1000 | W13: 1000 | X13: 0.04 | Y13: =W13*X13 -> 40 | Z13: =W13-V13 -> 0 | AA13: Pendiente | AC13: ESTIMADO: el BOM no define valor (impedancia/corriente). Precio típico de bead 0603 de potencia.
A14: 13 | B14: J1_PC104 | C14: Conector PC/104 hembra 52 pos, 2×26, 2.54 mm | D14: 1 | E14: SAMTEC_ESQ-126-12-G-D | F14: Samtec | G14: ESQ-126-12-G-D | H14: BOM (huella) | I14: COTIZADO | J14: Samtec directo / Digi-Key (SAM11112-ND) | K14: USD | L14: =$D14*10 -> 10 | M14: 16 | N14: 9.34 | O14: =M14*N14 -> 149.44 | P14: =M14-L14 -> 6 | Q14: =$D14*100 -> 100 | R14: 104 | S14: 7.332 | T14: =R14*S14 -> 762.528 | U14: =R14-Q14 -> 4 | V14: =$D14*1000 -> 1000 | W14: 1000 | X14: 5.508 | Y14: =W14*X14 -> 5508 | Z14: =W14-V14 -> 0 | AA14: En stock (32 uds 'ships tomorrow' + 151 distribuidor); empaque tubo de 8 | AB14: https://www.samtec.com/products/esq-126-12-g-d | AC14: Escalones Samtec: 1 $10.43, 10 $9.34, 100 $7.332, 1000 $5.508. Se compran múltiplos de 8 (tubo): lote 10 → 16 uds; lote 100 → 104 uds.
A15: 14 | B15: J_ACTUATORS | C15: Conector Harwin Gecko 1.25 mm, 2×6, hembra vertical | D15: 1 | E15: HARWIN_G125-FV11205L0P | F15: Harwin | G15: G125-FV11205L0P | H15: BOM (huella) | I15: COTIZADO | J15: Mouser (855-G125-FV11205L0P), vía espejo the-esb.com | K15: USD | L15: =$D15*10 -> 10 | M15: 10 | N15: 12.15 | O15: =M15*N15 -> 121.5 | P15: =M15-L15 -> 0 | Q15: =$D15*100 -> 100 | R15: 100 | S15: 10.59 | T15: =R15*S15 -> 1059 | U15: =R15-Q15 -> 0 | V15: =$D15*1000 -> 1000 | W15: 1000 | X15: 7.54 | Y15: =W15*X15 -> 7540 | Z15: =W15-V15 -> 0 | AA15: Mouser: 105 uds; TTI en pedido (plazo 13 sem) | AB15: https://the-esb.com/part/g125fv11205l0p~harwin | AC15: Mouser: 1 $13.71, 10 $12.15, 100 $10.59, 1K $7.54. TTI: 100 $9.28, 1K $7.48 (https://thepartsdirect.com/part/g125fv11205l0p~harwin). Lote 10 es el segundo ítem más caro.
A16: 15 | B16: R1-R5, R_a, R_CAM_RST, R_IMU_CS, R_MAG_SCL, R_MAG_SDA, R_OE_PULLDOWN, R_PULL_EN, R_SLEEP_X/Y/Z, Regf | C16: Resistor 10 kΩ ±1% 0.1 W 0603 | D16: 16 | E16: RESC1608X55X25ML10T15 | F16: Yageo | G16: RC0603FR-0710KL | H16: Propuesto | I16: ESTIMADO | J16: LCSC C98220 / RS (referencias) | K16: USD | L16: =$D16*10 -> 160 | M16: 160 | N16: 0.006 | O16: =M16*N16 -> 0.96 | P16: =M16-L16 -> 0 | Q16: =$D16*100 -> 1600 | R16: 1600 | S16: 0.004 | T16: =R16*S16 -> 6.4 | U16: =R16-Q16 -> 0 | V16: =$D16*1000 -> 16000 | W16: 16000 | X16: 0.002 | Y16: =W16*X16 -> 32 | Z16: =W16-V16 -> 0 | AA16: En stock (≈9 M en LCSC) | AB16: https://www.lcsc.com/product-image/C98220.html | AC16: LCSC lista precio desde $0.0008 a cantidad de carrete; RS UK £0.004–0.006 por RC0603FR-07xxx. Se usa un precio de pequeña cantidad (estimado).
A17: 16 | B17: R_COMP_2 | C17: Resistor 1 kΩ ±1% 0.1 W 0603 | D17: 1 | E17: RESC1608X55X25ML10T15 | F17: Yageo | G17: RC0603FR-071KL | H17: Propuesto | I17: ESTIMADO | J17: Referencia RS/LCSC | K17: USD | L17: =$D17*10 -> 10 | M17: 10 | N17: 0.006 | O17: =M17*N17 -> 0.06 | P17: =M17-L17 -> 0 | Q17: =$D17*100 -> 100 | R17: 100 | S17: 0.004 | T17: =R17*S17 -> 0.4 | U17: =R17-Q17 -> 0 | V17: =$D17*1000 -> 1000 | W17: 1000 | X17: 0.002 | Y17: =W17*X17 -> 2 | Z17: =W17-V17 -> 0 | AA17: En stock | AC17: Igual criterio que 10 kΩ.
A18: 17 | B18: R_I2C_SCL, R_I2C_SDA | C18: Resistor 1.5 kΩ ±0.1% 1/10 W 0603 (película delgada) | D18: 2 | E18: RES_ERA3ARB152V | F18: Panasonic | G18: ERA3ARB152V (BOM) → sucesor ERA-3AEB152V | H18: BOM (huella) | I18: ESTIMADO | J18: Master Electronics / RS / derf (referencias) | K18: USD | L18: =$D18*10 -> 20 | M18: 20 | N18: 0.108 | O18: =M18*N18 -> 2.16 | P18: =M18-L18 -> 0 | Q18: =$D18*100 -> 200 | R18: 200 | S18: 0.06 | T18: =R18*S18 -> 12 | U18: =R18-Q18 -> 0 | V18: =$D18*1000 -> 2000 | W18: 2000 | X18: 0.05 | Y18: =W18*X18 -> 100 | Z18: =W18-V18 -> 0 | AA18: ERA3ARB152V DESCONTINUADO en RS; ERA-3AEB152V: MOQ 5000 en Master (plazo 12 sem) | AB18: https://masterelectronics.com/en/panasonic/era3aeb152v-44450459.html | AC18: Master: 5000 @ $0.0287 (MOQ 5000). derf.com (ERA-3YEB152V): $0.108 @11–50. RS UK: £0.022 @500+. Los lotes 100/1000 son estimados entre esas referencias. Descontinuado: https://uk.rs-online.com/p/surface-mount-resistors/6618691
A19: 18 | B19: R_SENSE | C19: Shunt 100 mΩ ±1% 1 W 1206 AEC-Q200 metal | D19: 1 | E19: RESC3216X89N | F19: Vishay | G19: WSLP1206R1000FEA | H19: Propuesto | I19: ESTIMADO | J19: Farnell (familia WSLP1206, proxy USD) | K19: USD | L19: =$D19*10 -> 10 | M19: 10 | N19: 0.738 | O19: =M19*N19 -> 7.38 | P19: =M19-L19 -> 0 | Q19: =$D19*100 -> 100 | R19: 100 | S19: 0.508 | T19: =R19*S19 -> 50.8 | U19: =R19-Q19 -> 0 | V19: =$D19*1000 -> 1000 | W19: 1000 | X19: 0.373 | Y19: =W19*X19 -> 373 | Z19: =W19-V19 -> 0 | AA19: Familia en stock; verificar este valor | AB19: https://il.farnell.com/vishay/wslp12061l000fea/current-sense-res-0r001-1-1-w/dp/2420760 | AC19: PROXY: no se obtuvo la página del valor 100 mΩ; se usan los escalones del WSLP12061L000FEA (mismo tamaño/serie, 10+ $0.738, 100+ $0.508, 1000+ $0.373).
A20: 19 | B20: Reg_ | C20: Resistor 130 kΩ ±1% 0.1 W 0603 | D20: 1 | E20: RESC1608X55N | F20: Yageo | G20: RC0603FR-07130KL | H20: Propuesto | I20: ESTIMADO | J20: Referencia RS/LCSC | K20: USD | L20: =$D20*10 -> 10 | M20: 10 | N20: 0.006 | O20: =M20*N20 -> 0.06 | P20: =M20-L20 -> 0 | Q20: =$D20*100 -> 100 | R20: 100 | S20: 0.004 | T20: =R20*S20 -> 0.4 | U20: =R20-Q20 -> 0 | V20: =$D20*1000 -> 1000 | W20: 1000 | X20: 0.002 | Y20: =W20*X20 -> 2 | Z20: =W20-V20 -> 0 | AA20: En stock | AC20: Igual criterio que 10 kΩ.
A21: 20 | B21: Regulador | C21: Regulador/IC MSOP-8 (sin descripción, sin MPN en BOM) | D21: 1 | E21: MSOP-8_MS | F21: (vacío en BOM) | G21: SIN IDENTIFICAR — pendiente | H21: Propuesto | I21: ESTIMADO | J21: Sin cotización | K21: USD | L21: =$D21*10 -> 10 | M21: 10 | N21: 3 | O21: =M21*N21 -> 30 | P21: =M21-L21 -> 0 | Q21: =$D21*100 -> 100 | R21: 100 | S21: 3 | T21: =R21*S21 -> 300 | U21: =R21-Q21 -> 0 | V21: =$D21*1000 -> 1000 | W21: 1000 | X21: 3 | Y21: =W21*X21 -> 3000 | Z21: =W21-V21 -> 0 | AA21: Pendiente | AC21: PENDIENTE: el BOM no identifica el IC. Marcador de $3.00 (rango típico MSOP-8 regulador/PMIC $1.5–$5), sin descuento por volumen. Es la mayor incertidumbre del cálculo.
A22: 21 | B22: U1_CAM_PWR | C22: Load switch 5.5 V, 1.5 A, 90 mΩ con descarga ajustable | D22: 1 | E22: SOT65P210X110-6N | F22: Texas Instruments | G22: TPS22919DCKR | H22: Propuesto | I22: COTIZADO | J22: Digi-Key US (296-TPS22919DCKRCT-ND) | K22: USD | L22: =$D22*10 -> 10 | M22: 10 | N22: 0.133 | O22: =M22*N22 -> 1.33 | P22: =M22-L22 -> 0 | Q22: =$D22*100 -> 100 | R22: 100 | S22: 0.1 | T22: =R22*S22 -> 10 | U22: =R22-Q22 -> 0 | V22: =$D22*1000 -> 1000 | W22: 1000 | X22: 0.08261 | Y22: =W22*X22 -> 82.61 | Z22: =W22-V22 -> 0 | AA22: En stock (≈144 k uds); plazo 6 sem | AB22: https://www.digikey.com/en/products/detail/texas-instruments/TPS22919DCKR/10434801 | AC22: Identificado por la descripción exacta del BOM (TI TPS22919, SC70-6). DK: 1 $0.20, 10 $0.133, 100 $0.10, 1000 $0.08261.
A23: 22 | B23: U1_IMU | C23: IMU iNEMO 3D acel.+giro | D23: 1 | E23: FP-LGA-14L-DM00249496-MFG | F23: STMicroelectronics | G23: LSM6DSOXTR | H23: BOM | I23: COTIZADO | J23: Digi-Key US (497-18367-1-ND) | K23: USD | L23: =$D23*10 -> 10 | M23: 10 | N23: 3.487 | O23: =M23*N23 -> 34.87 | P23: =M23-L23 -> 0 | Q23: =$D23*100 -> 100 | R23: 100 | S23: 3.0519 | T23: =R23*S23 -> 305.19 | U23: =R23-Q23 -> 0 | V23: =$D23*1000 -> 1000 | W23: 1000 | X23: 2.78705 | Y23: =W23*X23 -> 2787.05 | Z23: =W23-V23 -> 0 | AA23: En stock en capturas previas (19–28 k); plazo 20–24 sem | AB23: https://www.digikey.com/en/products/detail/stmicroelectronics/LSM6DSOXTR/9841887 | AC23: DK: 1 $4.07, 10 $3.487, 100 $3.0519, 500 $2.81442, 1000 $2.78705. OJO: otras capturas/regiones muestran $3.51 (@1) a $7.36 (@1): precio volátil.
A24: 23 | B24: U1_MTQ_X, U2_MTQ_Y, U3_MTQ_Z | C24: Driver puente H 12 V, 1 A | D24: 3 | E24: SON50P200X200X80-9N | F24: Texas Instruments | G24: DRV8837CDSGR | H24: BOM | I24: COTIZADO | J24: Digi-Key US (296-47205-1-ND) | K24: USD | L24: =$D24*10 -> 30 | M24: 30 | N24: 0.4944 | O24: =M24*N24 -> 14.832 | P24: =M24-L24 -> 0 | Q24: =$D24*100 -> 300 | R24: 300 | S24: 0.40412 | T24: =R24*S24 -> 121.236 | U24: =R24-Q24 -> 0 | V24: =$D24*1000 -> 3000 | W24: 3000 | X24: 0.3543 | Y24: =W24*X24 -> 1062.9 | Z24: =W24-V24 -> 0 | AA24: En stock (≈72 k uds) | AB24: https://www.digikey.com/en/products/detail/texas-instruments/DRV8837CDSGR/7688215 | AC24: DK: 25 $0.4944, 250 $0.40412, 1000 $0.37214, carrete 3000 $0.3543. Lote 1000 = 3000 uds = 1 carrete completo (sin sobrante).
A25: 24 | B25: U2 | C25: Sensor de imagen CMOS 1.2 MP (color), iBGA-63 | D25: 1 | E25: BGA63C100P8X8_900X900X144N | F25: onsemi | G25: AR0135CS2C00SUEA0-DRBR | H25: BOM | I25: COTIZADO | J25: Digi-Key España — Marketplace (5556-AR0135CS2C00SUEA0-DRBR-ND) | K25: USD | L25: =$D25*10 -> 10 | M25: 10 | N25: =Supuestos!$B$4*Supuestos!$B$3 -> 23.7216 | O25: =M25*N25 -> 237.216 | P25: =M25-L25 -> 0 | Q25: =$D25*100 -> 100 | R25: 100 | S25: =Supuestos!$B$5*Supuestos!$B$3 -> 21.411264 | T25: =R25*S25 -> 2141.1264 | U25: =R25-Q25 -> 0 | V25: =$D25*1000 -> 1000 | W25: 1000 | X25: =Supuestos!$B$6*Supuestos!$B$3 -> 21.411264 | Y25: =W25*X25 -> 21411.264 | Z25: =W25-V25 -> 0 | AA25: Stock fábrica 2,600; plazo 20 sem; ítem Marketplace (vendedor externo) | AB25: https://www.digikey.es/en/products/detail/onsemi/AR0135CS2C00SUEA0-DRBR/7221084 | AC25: DK ES (EUR): 1 €23.93, 10 €21.18, 100 €19.1172. Sin escalón a 1000 → se mantiene €19.1172 (cota superior). Es el componente dominante del costo. Hay listados 'obsoletos' en otros sitios para variantes -DPBR/-DRBR1: confirmar ciclo de vida.
A26: 25 | B26: U2_MAG | C26: Magnetómetro 3 ejes MMC5983MA (IC) | D26: 1 | E26: PQFN50P300X300X100-16N | F26: MEMSIC | G26: MMC5983MA | H26: BOM | I26: COTIZADO | J26: Digi-Key US (1267-MMC5983MACT-ND) | K26: USD | L26: =$D26*10 -> 10 | M26: 10 | N26: 2.378 | O26: =M26*N26 -> 23.78 | P26: =M26-L26 -> 0 | Q26: =$D26*100 -> 100 | R26: 100 | S26: 2.0681 | T26: =R26*S26 -> 206.81 | U26: =R26-Q26 -> 0 | V26: =$D26*1000 -> 1000 | W26: 1000 | X26: 1.83604 | Y26: =W26*X26 -> 1836.04 | Z26: =W26-V26 -> 0 | AA26: En stock (≈29–68 k uds); plazo 8 sem | AB26: https://www.digikey.com/en/products/detail/memsic-inc/MMC5983MA/10452795 | AC26: La descripción del BOM dice 'Evaluation Board' (MMC5983MA-B, $20.95) pero el MPN es el IC: se cotiza el IC. Corregir descripción del BOM.
A27: 26 | B27: U3_LEVEL_SHIFTER, U4_LEVEL_SHIFTER | C27: Traductor de nivel bidireccional 20-TSSOP (PW0020A) | D27: 2 | E27: FP-PW0020A-IPC_A | F27: Texas Instruments | G27: TXS0108EPWR | H27: Propuesto | I27: COTIZADO | J27: Digi-Key US (296-23011-1-ND) | K27: USD | L27: =$D27*10 -> 20 | M27: 20 | N27: 1.108 | O27: =M27*N27 -> 22.16 | P27: =M27-L27 -> 0 | Q27: =$D27*100 -> 200 | R27: 200 | S27: 0.8928 | T27: =R27*S27 -> 178.56 | U27: =R27-Q27 -> 0 | V27: =$D27*1000 -> 2000 | W27: 2000 | X27: 0.82314 | Y27: =W27*X27 -> 1646.28 | Z27: =W27-V27 -> 0 | AA27: En stock (≈17 k uds) | AB27: https://www.digikey.com/en/products/detail/texas-instruments/TXS0108EPWR/1775302 | AC27: DK US: 10 $1.108, 100 $0.8928, 500 $0.82314. A 2000 uds no se ve el escalón de carrete en la captura: se usa el de 500 (cota superior). MPN propuesto: el BOM solo dice '8-bit bidireccional 20-TSSOP'.
A28: 27 | B28: U4_BLDC | C28: Driver BLDC 3 fases 8–60 V, 28-HTSSOP | D28: 1 | E28: FP-PWP0028C-IPC_A | F28: Texas Instruments | G28: DRV8313PWPR | H28: Propuesto | I28: COTIZADO | J28: Digi-Key (USD, sitio .com.mx) | K28: USD | L28: =$D28*10 -> 10 | M28: 10 | N28: 2.531 | O28: =M28*N28 -> 25.31 | P28: =M28-L28 -> 0 | Q28: =$D28*100 -> 100 | R28: 100 | S28: 2.0913 | T28: =R28*S28 -> 209.13 | U28: =R28-Q28 -> 0 | V28: =$D28*1000 -> 1000 | W28: 1000 | X28: 1.8609 | Y28: =W28*X28 -> 1860.9 | Z28: =W28-V28 -> 0 | AA28: En stock en capturas (≈2 k–5.7 k, otros 0); plazo 18 sem | AB28: https://www.digikey.com/en/products/detail/texas-instruments/DRV8313PWPR/3775439 | AC28: Precios USD leídos de la página digikey.com.mx (10 $2.531, 100 $2.0913, 1000 $1.8609, carrete 2000 $1.8161). Otros agregadores muestran $4.0–4.1 @1 (Mouser/TI). Verificar en vivo.
A29: TOTAL | D29: =SUM(D2:D28) -> 86 | O29: =SUM(O2:O28) -> 712.129 | T29: =SUM(T2:T28) -> 5655.0304 | Y29: =SUM(Y2:Y28) -> 49551.944

Sheet Fuentes
A1: Componente | B1: Proveedor | C1: URL | D1: Qué verificar
A2: AR0135CS2C00SUEA0-DRBR | B2: Digi-Key España (Marketplace) | C2: https://www.digikey.es/en/products/detail/onsemi/AR0135CS2C00SUEA0-DRBR/7221084 | D2: Tabla Tray EUR: 1/5/10/25/50/100
A3: LSM6DSOXTR | B3: Digi-Key US | C3: https://www.digikey.com/en/products/detail/stmicroelectronics/LSM6DSOXTR/9841887 | D3: Cut Tape USD
A4: MMC5983MA | B4: Digi-Key US | C4: https://www.digikey.com/en/products/detail/memsic-inc/MMC5983MA/10452795 | D4: Cut Tape USD
A5: DRV8837CDSGR | B5: Digi-Key US | C5: https://www.digikey.com/en/products/detail/texas-instruments/DRV8837CDSGR/7688215 | D5: Cut Tape y Tape&Reel USD
A6: DRV8313PWPR | B6: Digi-Key (.com.mx en USD) | C6: https://www.digikey.com/en/products/detail/texas-instruments/DRV8313PWPR/3775439 | D6: Cambiar país a México/USD si el sitio US muestra otra cosa
A7: TPS22919DCKR | B7: Digi-Key US | C7: https://www.digikey.com/en/products/detail/texas-instruments/TPS22919DCKR/10434801 | D7: Cut Tape USD
A8: TXS0108EPWR | B8: Digi-Key US | C8: https://www.digikey.com/en/products/detail/texas-instruments/TXS0108EPWR/1775302 | D8: Cut Tape USD
A9: ESQ-126-12-G-D | B9: Samtec / Digi-Key | C9: https://www.samtec.com/products/esq-126-12-g-d | D9: Breaks 1/10/25/50/100/500/1000/2000; Mult 8
A10: ESQ-126-12-G-D | B10: Digi-Key | C10: https://www.digikey.com/en/products/detail/samtec-inc/ESQ-126-12-G-D/6694915 | D10: Empaque estándar 8, $10.43 @1
A11: G125-FV11205L0P | B11: Mouser (espejo the-esb.com) | C11: https://the-esb.com/part/g125fv11205l0p~harwin | D11: Mouser 855-G125-FV11205L0P
A12: G125-FV11205L0P | B12: TTI (espejo thepartsdirect) | C12: https://thepartsdirect.com/part/g125fv11205l0p~harwin | D12: 100 $9.28, 1K $7.48
... A23: EUR→USD | B23: moneyexchangerate.org | C23: https://moneyexchangerate.org/currencyexchange/eur/usd/6 | D23: 1 EUR = 1.12 USD (20-oct-2026)
